twitterpeel.py
twitterpeel-0.2.0.dist-info/LICENSE
twitterpeel-0.2.0.dist-info/METADATA
twitterpeel-0.2.0.dist-info/WHEEL
twitterpeel-0.2.0.dist-info/top_level.txt
twitterpeel-0.2.0.dist-info/RECORD
