Metadata-Version: 2.1
Name: twitterpeel
Version: 0.2.0
Summary: Twitter frontend API scraper
Home-page: https://github.com/kylepw/twitterpeel
Author: Kyle Weeks
Author-email: kylepw@gmail.com
License: MIT License
Platform: UNKNOWN
Classifier: Natural Language :: English
Classifier: Programming Language :: Python :: 3
Classifier: License :: OSI Approved :: MIT License
Requires-Dist: BeautifulSoup4
Requires-Dist: lxml
Requires-Dist: requests
